pushikoo/__init__.py
pushikoo/app.py
pushikoo/alembic/README
pushikoo/alembic/env.py
pushikoo/alembic/script.py.mako
pushikoo/alembic/versions/375e5d19af3c_cron_use_flow.py
pushikoo/alembic/versions/3a95bd2df2c0_add_flownodeexecution.py
pushikoo/alembic/versions/626aa6a4605a_add_name_field_for_flow.py
pushikoo/alembic/versions/901b1c885e43_flow_nodes_json_drop_flowstep.py
pushikoo/alembic/versions/a0d262bbb668_add_flowinstance.py
pushikoo/alembic/versions/bfbf041984e0_initial_migration.py
pushikoo/alembic/versions/c3e7f9a1b2d4_rename_pip_extra_index_url_to_pip_index.py
pushikoo/alembic/versions/eb24b504aa11_refactor_file_table.py
pushikoo/alembic/versions/fbaa7dfbb82f_add_created_at_to_flowinstance.py
pushikoo/alembic/versions/ff5d41ab4149_add_enabled_field_to_flowcron.py
pushikoo/api/__init__.py
pushikoo/api/security.py
pushikoo/api/spa.py
pushikoo/api/v1/__init__.py
pushikoo/api/v1/adapter.py
pushikoo/api/v1/cron.py
pushikoo/api/v1/file.py
pushikoo/api/v1/flow.py
pushikoo/api/v1/instance.py
pushikoo/api/v1/message.py
pushikoo/api/v1/oauth.py
pushikoo/api/v1/pip.py
pushikoo/api/v1/system.py
pushikoo/api/v1/warning.py
pushikoo/db/__init__.py
pushikoo/frontend-static/favicon.ico
pushikoo/frontend-static/index.html
pushikoo/frontend-static/assets/LoadingSpinner-JK0Z87-_.css
pushikoo/frontend-static/assets/LoadingSpinner.vue_vue_type_style_index_0_scoped_0c8a0411_lang-D_MGrIbP.js
pushikoo/frontend-static/assets/SchemaForm-Dd2o4P-y.js
pushikoo/frontend-static/assets/SchemaForm-L_kr5xMI.css
pushikoo/frontend-static/assets/VAlert-Qkf0eDNA.css
pushikoo/frontend-static/assets/VAlert-lJiK8Tm2.js
pushikoo/frontend-static/assets/VAutocomplete-2QiI03gj.js
pushikoo/frontend-static/assets/VAutocomplete-C9NL5_uo.css
pushikoo/frontend-static/assets/VCheckbox-CvH8ekHL.css
pushikoo/frontend-static/assets/VCheckbox-DNMaH8v3.js
pushikoo/frontend-static/assets/VContainer-COAOQEyp.css
pushikoo/frontend-static/assets/VContainer-Dp3Q7MEs.js
pushikoo-0.10.2.dist-info/METADATA
pushikoo-0.10.2.dist-info/WHEEL
pushikoo-0.10.2.dist-info/entry_points.txt
pushikoo-0.10.2.dist-info/RECORD
