Metadata-Version: 2.4
Name: pushikoo
Version: 0.10.2
Summary: A message synchronization framework.
Project-URL: Homepage, https://github.com/Pushikoo/Pushikoo
Author: Pushikoo
Classifier: Operating System :: OS Independent
Classifier: Programming Language :: Python :: 3
Requires-Python: ==3.12.*
Requires-Dist: alembic<2.0.0,>=1.17.2
Requires-Dist: apscheduler<4.0.0,>=3.11.1
Requires-Dist: authlib<2.0.0,>=1.6.6
Requires-Dist: diskcache<6.0.0,>=5.6.3
Requires-Dist: fastapi<0.125.0,>=0.124.4
Requires-Dist: httpx<0.29.0,>=0.28.1
Requires-Dist: itsdangerous<3.0.0,>=2.2.0
Requires-Dist: loguru<0.8.0,>=0.7.3
Requires-Dist: pillow<13.0.0,>=12.0.0
Requires-Dist: pushikoo-adapter-testgetter
Requires-Dist: pushikoo-adapter-testprocesser
Requires-Dist: pushikoo-adapter-testpusher
Requires-Dist: pushikoo-interface>=1.0.2
Requires-Dist: pydantic-settings<3.0.0,>=2.12.0
Requires-Dist: pydantic<3.0.0,>=2.12.4
Requires-Dist: pyjwt[crypto]>=2.10.1
Requires-Dist: python-multipart<0.0.21,>=0.0.20
Requires-Dist: requests<3.0.0,>=2.32.5
Requires-Dist: sqlalchemy-utc>=0.14.0
Requires-Dist: sqlalchemy<3.0.0,>=2.0.45
Requires-Dist: sqlmodel<0.0.28,>=0.0.27
Requires-Dist: starlette<0.51.0,>=0.50.0
Requires-Dist: uvicorn<0.39.0,>=0.38.0
Provides-Extra: build
Requires-Dist: hatch>=1.16.2; extra == 'build'
Provides-Extra: dev
Requires-Dist: pip-audit>=2.10.0; extra == 'dev'
Requires-Dist: pytest; extra == 'dev'
Requires-Dist: ruff; extra == 'dev'
